<?xml version="1.0" encoding="UTF-8" standalone="no"?>
<CreditNote xmlns="urn:oasis:names:specification:ubl:schema:xsd:CreditNote-2"
	xmlns:cac="urn:oasis:names:specification:ubl:schema:xsd:CommonAggregateComponents-2"
	xmlns:cbc="urn:oasis:names:specification:ubl:schema:xsd:CommonBasicComponents-2"
	xmlns:ds="http://www.w3.org/2000/09/xmldsig#"
	xmlns:ext="urn:oasis:names:specification:ubl:schema:xsd:CommonExtensionComponents-2"
	xmlns:sts="dian:gov:co:facturaelectronica:Structures-2-1"
	xmlns:xades="http://uri.etsi.org/01903/v1.3.2#"
	xmlns:xades141="http://uri.etsi.org/01903/v1.4.1#"
	xmlns:xsi="http://www.w3.org/2001/XMLSchema-instance"
	xsi:schemaLocation="urn:oasis:names:specification:ubl:schema:xsd:CreditNote-2    http://docs.oasis-open.org/ubl/os-UBL-2.1/xsd/maindoc/UBL-CreditNote-2.1.xsd">
	<ext:UBLExtensions>
		<ext:UBLExtension>
			<ext:ExtensionContent>
				<sts:DianExtensions>
					<sts:InvoiceSource>
						<cbc:IdentificationCode listAgencyID="6"
							listAgencyName="United Nations Economic Commission for Europe"
							listSchemeURI="urn:oasis:names:specification:ubl:codelist:gc:CountryIdentificationCode-2.1">CO</cbc:IdentificationCode>
					</sts:InvoiceSource>
					<sts:SoftwareProvider>
						<sts:ProviderID schemeAgencyID="195"
							schemeAgencyName="CO, DIAN (Dirección de Impuestos y Aduanas Nacionales)"
							schemeID="{{ProviderIDschemeID}}"
							schemeName="{{ProviderIDschemeName}}">{{ProviderID}}</sts:ProviderID>
						<sts:SoftwareID schemeAgencyID="195"
							schemeAgencyName="CO, DIAN (Dirección de Impuestos y Aduanas Nacionales)">{{SoftwareID}}</sts:SoftwareID>
					</sts:SoftwareProvider>
					<sts:SoftwareSecurityCode schemeAgencyID="195"
						schemeAgencyName="CO, DIAN (Dirección de Impuestos y Aduanas Nacionales)">{{SoftwareSecurityCode}}</sts:SoftwareSecurityCode>
					<sts:AuthorizationProvider>
						<sts:AuthorizationProviderID schemeAgencyID="195"
							schemeAgencyName="CO, DIAN (Dirección de Impuestos y Aduanas Nacionales)"
							schemeID="4"
							schemeName="31">800197268</sts:AuthorizationProviderID>
					</sts:AuthorizationProvider>
					<sts:QRCode>NumNAS: {{ID}}
						FecNAS: {{IssueDate}}
						HorNAS: {{IssueTime}}
						NumSNO: {{AccountingSupplierParty.CompanyID}}
						DocABS: {{AccountingCustomerParty.CompanyID}}
						ValNAS: {{LineExtensionAmount}}
						ValIva: {{ValIva}}
						ValTolNAS: {{PayableAmount}}
						CUDS: {{UUID}}
						URL: {{QRCodeURL}}</sts:QRCode>
				</sts:DianExtensions>
			</ext:ExtensionContent>
		</ext:UBLExtension>
		<ext:UBLExtension>
			<ext:ExtensionContent/>
		</ext:UBLExtension>
	</ext:UBLExtensions>
	<cbc:UBLVersionID>UBL 2.1</cbc:UBLVersionID>
	<cbc:CustomizationID>{{CustomizationID}}</cbc:CustomizationID>
	<cbc:ProfileID>"DIAN 2.1: Nota de ajuste al documento soporte en adquisiciones efectuadas a sujetos no obligados a expedir factura o documento equivalente </cbc:ProfileID>
	<cbc:ProfileExecutionID>{{ProfileExecutionID}}</cbc:ProfileExecutionID>
	<cbc:ID>{{ID}}</cbc:ID>
	<cbc:UUID schemeID="{{ProfileExecutionID}}" schemeName="CUDS-SHA384">{{UUID}}</cbc:UUID>
	<cbc:IssueDate>{{IssueDate}}</cbc:IssueDate>
	<cbc:IssueTime>{{IssueTime}}</cbc:IssueTime>
	<cbc:CreditNoteTypeCode>{{CreditNoteTypeCode}}</cbc:CreditNoteTypeCode>
	<!--TODO 1.0: Que nota colocar?-->
	<cbc:Note>{{Note}}</cbc:Note>
	<cbc:DocumentCurrencyCode listAgencyID="6"
		listAgencyName="United Nations Economic Commission for Europe"
		listID="ISO 4217 Alpha">{{DocumentCurrencyCode}}</cbc:DocumentCurrencyCode>
	<cbc:LineCountNumeric>{{LineCountNumeric}}</cbc:LineCountNumeric>
	<cac:DiscrepancyResponse>
		<cbc:ReferenceID>{{DiscrepancyReferenceID}}</cbc:ReferenceID>
		<cbc:ResponseCode>{{DiscrepancyResponseCode}}</cbc:ResponseCode>
		<cbc:Description>{{DiscrepancyDescription}}</cbc:Description>
	</cac:DiscrepancyResponse>
	<!--TODO 1.0 TODAS LAS FACTURAS DEBEN SER DEL MISMO ADQUIRIENTE-->
	<!--Si CreditNoteTypeCode igual a 20 es obligatorio-->
	{% if BillingReference.ID %}
	<cac:BillingReference>
		<cac:InvoiceDocumentReference>
			<cbc:ID>{{BillingReference.ID}}</cbc:ID>
			<cbc:UUID schemeName="CUDS-SHA384">{{BillingReference.UUID}}</cbc:UUID>
			<cbc:IssueDate>{{BillingReference.IssueDate}}</cbc:IssueDate>
		</cac:InvoiceDocumentReference>
	</cac:BillingReference>
	{% endif %}
	<!--TODO 2.0: Si se habilita sale Error Regla ZB01>
	<cac:OrderReference>
		<cbc:ID>{{OrderReferenceID}}</cbc:ID>
		<cbc:IssueDate>{{OrderReferenceIssueDate}}</cbc:IssueDate>
	</cac:OrderReference-->
	<cac:AccountingSupplierParty>
		<cbc:AdditionalAccountID schemeID="01">{{AccountingSupplierParty.AdditionalAccountID}}</cbc:AdditionalAccountID>
		<cac:Party>
			<cac:PhysicalLocation>
				<cac:Address>
					{% if AccountingSupplierParty.AddressID %}
					<cbc:ID>{{AccountingSupplierParty.AddressID}}</cbc:ID>
					{% endif %}
					<cbc:CityName>{{AccountingSupplierParty.AddressCityName}}</cbc:CityName>
					{% if AccountingSupplierParty.AddressPostalZone %}
					<cbc:PostalZone>{{AccountingSupplierParty.AddressPostalZone}}</cbc:PostalZone>
					{% endif %}
					{% if AccountingSupplierParty.AddressCountrySubentity %}
					<cbc:CountrySubentity>{{AccountingSupplierParty.AddressCountrySubentity}}</cbc:CountrySubentity>
					{% endif %}
					{% if AccountingSupplierParty.AddressCountrySubentityCode %}
					<cbc:CountrySubentityCode>{{AccountingSupplierParty.AddressCountrySubentityCode}}</cbc:CountrySubentityCode>
					{% endif %}
					<!--TODO 2.0: Puede iterar porque puede tener mas direcciones o infoirmacion adicional de la direccion-->
					<cac:AddressLine>
						<cbc:Line>{{AccountingSupplierParty.AddressLine}}</cbc:Line>
					</cac:AddressLine>
					<cac:Country>
						<cbc:IdentificationCode>{{AccountingSupplierParty.CountryIdentificationCode}}</cbc:IdentificationCode>
						<!--TODO 2.0: languageID podria variar, siguiente version revisar esto-->
						<cbc:Name languageID="es">{{AccountingSupplierParty.CountryName}}</cbc:Name>
					</cac:Country>
				</cac:Address>
			</cac:PhysicalLocation>
			<cac:PartyTaxScheme>
				<cbc:RegistrationName>{{AccountingSupplierParty.RegistrationName}}</cbc:RegistrationName>
				<cbc:CompanyID schemeAgencyID="195"
					schemeAgencyName="CO, DIAN (Dirección de Impuestos y Aduanas Nacionales)"
					{% if DV %}schemeID="{{DV}}"{% endif %}
					{% if CustomizationID != '10' %}schemeName="{{AccountingSupplierParty.CompanyIDschemeName}}"{% endif %}
					{% if CustomizationID == '10' %}schemeName="31"{% endif %}>{{AccountingSupplierParty.CompanyID}}</cbc:CompanyID>
				<!--TODO 2.0: listName el anexo no aparece, en la ejemplificacion si-->
				<cbc:TaxLevelCode listName="{{AccountingSupplierParty.listName}}">{{AccountingSupplierParty.TaxLevelCode}}</cbc:TaxLevelCode>
				<cac:TaxScheme>
					<cbc:ID>{{AccountingSupplierParty.TaxSchemeID}}</cbc:ID>
					<cbc:Name>{{AccountingSupplierParty.TaxSchemeName}}</cbc:Name>
				</cac:TaxScheme>
			</cac:PartyTaxScheme>
		</cac:Party>
	</cac:AccountingSupplierParty>
	<cac:AccountingCustomerParty>
		<cbc:AdditionalAccountID>{{AccountingCustomerParty.AdditionalAccountID}}</cbc:AdditionalAccountID>
		<cac:Party>
			<cac:PartyTaxScheme>
				<cbc:RegistrationName>{{AccountingCustomerParty.RegistrationName}}</cbc:RegistrationName>
				<cbc:CompanyID schemeAgencyID="195"
					schemeAgencyName="CO, DIAN (Dirección de Impuestos y Aduanas Nacionales)"
					{% if AccountingCustomerParty.CompanyIDschemeName == '31' %}schemeID="{{AccountingCustomerParty.CompanyIDschemeID}}"{% endif %}
					schemeName="{{AccountingCustomerParty.CompanyIDschemeName}}">{{AccountingCustomerParty.CompanyID}}</cbc:CompanyID>
				<!--TODO 2.0: listName el anexo no aparece, en la ejemplificacion si-->
				<cbc:TaxLevelCode listName="{{AccountingCustomerParty.listName}}">{{AccountingCustomerParty.TaxLevelCode}}</cbc:TaxLevelCode>
				<cac:TaxScheme>
					<cbc:ID>{{AccountingCustomerParty.TaxSchemeID}}</cbc:ID>
					<cbc:Name>{{AccountingCustomerParty.TaxSchemeName}}</cbc:Name>
				</cac:TaxScheme>
			</cac:PartyTaxScheme>
		</cac:Party>
	</cac:AccountingCustomerParty>
	<!--TODO 2.0: Puede iterar-->
	<cac:PaymentMeans>
		<cbc:ID>{{PaymentMeansID}}</cbc:ID>
		<cbc:PaymentMeansCode>{{PaymentMeansCode}}</cbc:PaymentMeansCode>
		{% if PaymentDueDate %}
		<cbc:PaymentDueDate>{{PaymentDueDate}}</cbc:PaymentDueDate>
		{% endif %}
		<!--TODO 2.0: Identificador del pago, pueden ir de cero a varios PaymentID-->
		<!--cbc:PaymentID></cbc:PaymentID-->
	</cac:PaymentMeans>
	{% if DocumentCurrencyCode != 'COP' %}
	<cac:PaymentExchangeRate>
		<cbc:SourceCurrencyCode>{{PaymentExchangeRate.SourceCurrencyCode}}</cbc:SourceCurrencyCode>
		{% if 1.00 %}
		<cbc:SourceCurrencyBaseRate>1.00</cbc:SourceCurrencyBaseRate>
		{% endif %}
		<cbc:TargetCurrencyCode>{{PaymentExchangeRate.TargetCurrencyCode}}</cbc:TargetCurrencyCode>
		<cbc:TargetCurrencyBaseRate>1.00</cbc:TargetCurrencyBaseRate>
		<cbc:CalculationRate>{{'{:.2f}'.format(PaymentExchangeRate.CalculationRate)}}</cbc:CalculationRate>
		<cbc:Date>{{PaymentExchangeRate.Date}}</cbc:Date>
	</cac:PaymentExchangeRate>
	{% endif %}
	<!--TODO 3.0: Grupo de campos para información relacionadas con un cargo o un descuento>
	<cac:AllowanceCharge>
		<cbc:ID>SFR3123856</cbc:ID>
		<cbc:ChargeIndicator></cbc:ChargeIndicator>
		<cbc:AllowanceChargeReasonCode></cbc:AllowanceChargeReasonCode>
		<cbc:AllowanceChargeReason></cbc:AllowanceChargeReason>
		<cbc:MultiplierFactorNumeric>Prepago recibido</cbc:MultiplierFactorNumeric>
		<cbc:Amount currencyID="{{DocumentCurrencyCode}}">1000.00</cbc:Amount>
		<cbc:BaseAmount currencyID="{{DocumentCurrencyCode}}">1000.00</cbc:BaseAmount>
	</cac:AllowanceCharge-->
	{% for TaxTotalID, TaxTotal in TaxesTotal.items() %}
	{% if TaxTotal.total != 0 %}
	<cac:TaxTotal>
		<cbc:TaxAmount currencyID="{{DocumentCurrencyCode}}">{{'{:.2f}'.format(TaxTotal.total)}}</cbc:TaxAmount>
		{% for Percent, TaxSubtotal in TaxTotal.taxes.items() %}
		<cac:TaxSubtotal>
			<cbc:TaxableAmount currencyID="{{DocumentCurrencyCode}}">{{'{:.2f}'.format(TaxSubtotal.base)}}</cbc:TaxableAmount>
			<cbc:TaxAmount currencyID="{{DocumentCurrencyCode}}">{{'{:.2f}'.format(TaxSubtotal.amount)}}</cbc:TaxAmount>
			<cac:TaxCategory>
				<cbc:Percent>{{Percent}}</cbc:Percent>
				<cac:TaxScheme>
					<cbc:ID>{{TaxTotalID}}</cbc:ID>
					<cbc:Name>{{TaxTotal.name}}</cbc:Name>
				</cac:TaxScheme>
			</cac:TaxCategory>
		</cac:TaxSubtotal>
		{% endfor %}
	</cac:TaxTotal>
	{% endif %}
	{% endfor %}
	<cac:LegalMonetaryTotal>
		<cbc:LineExtensionAmount currencyID="{{DocumentCurrencyCode}}">{{LineExtensionAmount}}</cbc:LineExtensionAmount>
		<cbc:TaxExclusiveAmount currencyID="{{DocumentCurrencyCode}}">{{TaxExclusiveAmount}}</cbc:TaxExclusiveAmount>
		<cbc:TaxInclusiveAmount currencyID="{{DocumentCurrencyCode}}">{{TaxInclusiveAmount}}</cbc:TaxInclusiveAmount>
		<!--TODO 3.0: AllowanceTotalAmount == 0 y ChargeTotalAmount == 0 mientras tanto, suma de AllowanceCharge
		TaxInclusiveAmount == PayableAmount mientras tanto-->
		<cbc:AllowanceTotalAmount currencyID="{{DocumentCurrencyCode}}">0.00</cbc:AllowanceTotalAmount>
		<cbc:ChargeTotalAmount currencyID="{{DocumentCurrencyCode}}">0.00</cbc:ChargeTotalAmount>
		<cbc:PayableAmount currencyID="{{DocumentCurrencyCode}}">{{PayableAmount}}</cbc:PayableAmount>
	</cac:LegalMonetaryTotal>
	{% for CreditNoteLineID, CreditNoteLine in CreditNoteLines.items() %}
	<cac:CreditNoteLine>
		<cbc:ID>{{CreditNoteLineID}}</cbc:ID>
		<!--TODO 3.0: opcional
		<cbc:Note>Información Adicional: Texto libre para añadir información adicional al artículo.</cbc:Note-->
		<cbc:CreditedQuantity unitCode="{{CreditNoteLine.unitCode}}">{{CreditNoteLine.Quantity}}</cbc:CreditedQuantity>
		<cbc:LineExtensionAmount currencyID="{{DocumentCurrencyCode}}">{{CreditNoteLine.LineExtensionAmount}}</cbc:LineExtensionAmount>
		{% for TaxTotalID, TaxTotal in CreditNoteLine.TaxesTotal.items() %}
		{% if TaxTotal.total != 0 %}
		<cac:TaxTotal>
			<cbc:TaxAmount currencyID="{{DocumentCurrencyCode}}">{{'{:.2f}'.format(TaxTotal.total)}}</cbc:TaxAmount>
			{% for Percent, TaxSubtotal in TaxTotal.taxes.items() %}
			<cac:TaxSubtotal>
				<cbc:TaxableAmount currencyID="{{DocumentCurrencyCode}}">{{'{:.2f}'.format(TaxSubtotal.base)}}</cbc:TaxableAmount>
				<cbc:TaxAmount currencyID="{{DocumentCurrencyCode}}">{{'{:.2f}'.format(TaxSubtotal.amount)}}</cbc:TaxAmount>
				<cac:TaxCategory>
					<cbc:Percent>{{Percent}}</cbc:Percent>
					<cac:TaxScheme>
						<cbc:ID>{{TaxTotalID}}</cbc:ID>
						<cbc:Name>{{TaxTotal.name}}</cbc:Name>
					</cac:TaxScheme>
				</cac:TaxCategory>
			</cac:TaxSubtotal>
			{% endfor %}
		</cac:TaxTotal>
		{% endif %}
		{% endfor %}
		<!--TODO 2.0, puede iterar en el campo ID aumenta segun la cantidad de descuentos o cargos por lineas
		ChargeIndicator true seria un cargo-->
		{% if CreditNoteLine.AllowanceChargeAmount != '0.00' %}
		<cac:AllowanceCharge>
			<cbc:ID>1</cbc:ID>
			<cbc:ChargeIndicator>false</cbc:ChargeIndicator>
			<cbc:AllowanceChargeReason>Descuento Linea</cbc:AllowanceChargeReason>
			<cbc:MultiplierFactorNumeric>{{CreditNoteLine.MultiplierFactorNumeric}}</cbc:MultiplierFactorNumeric>
			<cbc:Amount currencyID="{{DocumentCurrencyCode}}">{{CreditNoteLine.AllowanceChargeAmount}}</cbc:Amount>
			<cbc:BaseAmount currencyID="{{DocumentCurrencyCode}}">{{CreditNoteLine.AllowanceChargeBaseAmount}}</cbc:BaseAmount>
		</cac:AllowanceCharge>
		{% endif %}
		<cac:Item>
			<!--TODO 2.0, puede haber hasta 3 descripciones-->
			<cbc:Description>{{CreditNoteLine.ItemDescription}}</cbc:Description>
			<!--TODO 2.0, Cantidad de unidad de este artículo por empaque>
			<cbc:PackSizeNumeric>{{InvoiceLine.PackSizeNumeric}}</cbc:PackSizeNumeric-->
			<!--TODO 2.0, puede haber hasta 3 marcas-->
			{% if CreditNoteLine.BrandName %}
			<cbc:BrandName>{{CreditNoteLine.BrandName}}</cbc:BrandName>
			{% endif %}
			<!--TODO 2.0, puede haber hasta 3 modelos
			Mandaremos la referencia del fabricante por ahora, hay que definir luego si esto cambia-->
			{% if CreditNoteLine.ModelName %}
			<cbc:ModelName>{{CreditNoteLine.ModelName}}</cbc:ModelName>
			{% endif %}
			<!--TODO 2.0, Grupo de datos de identificación del artículo o servicio de acuerdo con el vendedor>
			<cac:SellersItemIdentification>
				<cbc:ID>AOHV84-225</cbc:ID>
				<cbc:ExtendedID>AOHV84-225</cbc:ExtendedID>
			</cac:SellersItemIdentification-->
			<!--TODO 2.0, Grupo de datos de identificación del artículo o servicio de acuerdo con un estándar-->
			<!--OPCIONAL schemeName="Estándar de adopción del contribuyente" schemeAgencyID="" schemeAgencyName=""-->
			<cac:StandardItemIdentification>
				<cbc:ID schemeID="999">{{CreditNoteLine.StandardItemIdentification}}</cbc:ID>
			</cac:StandardItemIdentification>
		</cac:Item>
		<cac:Price>
			<cbc:PriceAmount currencyID="{{DocumentCurrencyCode}}">{{CreditNoteLine.PriceAmount}}</cbc:PriceAmount>
			<cbc:BaseQuantity unitCode="{{CreditNoteLine.unitCode}}">{{CreditNoteLine.Quantity}}</cbc:BaseQuantity>
		</cac:Price>
	</cac:CreditNoteLine>
	{% endfor %}
</CreditNote>
